[
  {
    "venue": "Yokohama Arena",
    "url": "http://www.yokohama-arena.co.jp",
    "reason": "No gigs found"
  },
  {
    "venue": "Spiral Hall",
    "url": "http://www.spiral.co.jp/s_rental/hall/",
    "reason": "No gigs found"
  },
  {
    "venue": "Tokyo Club",
    "url": "http://www.tokyo-club.com/meguro/about/",
    "reason": "No gigs found"
  },
  {
    "venue": "Crocodile",
    "url": "http://www.crocodile-live.jp",
    "reason": "No gigs found"
  },
  {
    "venue": "Club 251",
    "url": "http://www.club251.com",
    "reason": "No gigs found"
  },
  {
    "venue": "ZINC",
    "url": "http://music.geocities.jp/zinc_asakusa/index.html",
    "reason": "No gigs found"
  },
  {
    "venue": "Pumpkin",
    "url": "http://www.geocities.jp/livehouse_pumpkin/",
    "reason": "No gigs found"
  },
  {
    "venue": "Laforet Museum Harajuku",
    "url": "http://www.laforet.ne.jp/news_events/",
    "reason": "No gigs found"
  },
  {
    "venue": "Saitama Arts Theater",
    "url": "https://www.saf.or.jp/en/venues/arthall/",
    "reason": "No gigs found"
  },
  {
    "venue": "Artica 7",
    "url": "http://www.artica7.live/",
    "reason": "No gigs found"
  },
  {
    "venue": "LIVE HAUS",
    "url": "http://livehaus.jp",
    "reason": "No gigs found"
  },
  {
    "venue": "Crazy Cats",
    "url": "http://www.crazycats.org/livehouse/",
    "reason": "No gigs found"
  },
  {
    "venue": "Cafe & Diner Studio",
    "url": "https://clubberia.com/en/preserve/CAFE/studio1.html",
    "reason": "No gigs found"
  },
  {
    "venue": "Zippal Hall",
    "url": "http://www.miyaji.co.jp/zippalhall",
    "reason": "No gigs found"
  },
  {
    "venue": "Rocky Top",
    "url": "http://www.liverocky.com/index2.html",
    "reason": "No gigs found"
  },
  {
    "venue": "Rinky Dink Studio (Hachioji 1st)",
    "url": "http://www.rinky.info/studio/hachiouji1/",
    "reason": "No gigs found"
  }
]